multibaas_sdk/__init__.py
multibaas_sdk/api_client.py
multibaas_sdk/api_response.py
multibaas_sdk/configuration.py
multibaas_sdk/exceptions.py
multibaas_sdk/py.typed
multibaas_sdk/rest.py
multibaas_sdk/api/__init__.py
multibaas_sdk/api/addresses_api.py
multibaas_sdk/api/admin_api.py
multibaas_sdk/api/chains_api.py
multibaas_sdk/api/contracts_api.py
multibaas_sdk/api/event_queries_api.py
multibaas_sdk/api/events_api.py
multibaas_sdk/api/hsm_api.py
multibaas_sdk/api/txm_api.py
multibaas_sdk/api/webhooks_api.py
multibaas_sdk/models/__init__.py
multibaas_sdk/models/accept_invite200_response.py
multibaas_sdk/models/accept_invite_request.py
multibaas_sdk/models/access_tuple.py
multibaas_sdk/models/add_key.py
multibaas_sdk/models/address.py
multibaas_sdk/models/address_alias.py
multibaas_sdk/models/api_key.py
multibaas_sdk/models/api_key_with_secret.py
multibaas_sdk/models/audit_log.py
multibaas_sdk/models/authorization_extra_info.py
multibaas_sdk/models/azure_account.py
multibaas_sdk/models/azure_hardware_wallet.py
multibaas_sdk/models/azure_wallet.py
multibaas_sdk/models/base_api_key.py
multibaas_sdk/models/base_azure_account.py
multibaas_sdk/models/base_contract.py
multibaas_sdk/models/base_response.py
multibaas_sdk/models/base_user.py
multibaas_sdk/models/base_webhook_endpoint.py
multibaas_sdk/models/block.py
multibaas_sdk/models/call_contract_function200_response.py
multibaas_sdk/models/call_contract_function200_response_all_of_result.py
multibaas_sdk/models/chain_name.py
multibaas_sdk/models/chain_status.py
multibaas_sdk/models/cloud_wallet_txto_sign.py
multibaas_sdk/models/cloud_wallet_txto_sign_tx.py
multibaas_sdk/models/contract.py
multibaas_sdk/models/contract_abi.py
multibaas_sdk/models/contract_abi_error.py
multibaas_sdk/models/contract_abi_error_argument.py
multibaas_sdk/models/contract_abi_event.py
multibaas_sdk/models/contract_abi_event_argument.py
multibaas_sdk/models/contract_abi_method.py
multibaas_sdk/models/contract_abi_method_argument.py
multibaas_sdk-1.0.1.dist-info/licenses/LICENSE
multibaas_sdk-1.0.1.dist-info/METADATA
multibaas_sdk-1.0.1.dist-info/WHEEL
multibaas_sdk-1.0.1.dist-info/top_level.txt
multibaas_sdk-1.0.1.dist-info/RECORD
