Metadata-Version: 2.4
Name: multibaas_sdk
Version: 1.0.1
Summary: MultiBaas API
Home-page: https://github.com/curvegrid/multibaas-sdk-python
Author: Curvegrid
Author-email: Curvegrid <contact@curvegrid.com>
License-Expression: MIT
Project-URL: Repository, https://github.com/curvegrid/multibaas-sdk-python
Keywords: OpenAPI,OpenAPI-Generator,MultiBaas API
Requires-Python: >=3.9
License-File: LICENSE
Requires-Dist: urllib3<3.0.0,>=2.1.0
Requires-Dist: python-dateutil>=2.8.2
Requires-Dist: pydantic>=2
Requires-Dist: typing-extensions>=4.7.1
Dynamic: author
Dynamic: home-page
Dynamic: license-file
